.gitignore
MESSAGES.rst
Makefile
README.rst
TODO.rst
mapper.cfg.sample
mudpyc.xml
run
setup.py
config/Midnight Sun 2.cfg
config/Morgengrauen.cfg
doc/hacking.rst
doc/mapper.de.rst
doc/mapper.rst
doc/mudlet.rst
example/basic.py
locales/mudpyc.pot
locales/de/LC_MESSAGES/mudpyc.po
mudpyc/__init__.py
mudpyc/alias.py
mudpyc/server.py
mudpyc/util.py
mudpyc.egg-info/PKG-INFO
mudpyc.egg-info/SOURCES.txt
mudpyc.egg-info/dependency_links.txt
mudpyc.egg-info/requires.txt
mudpyc.egg-info/top_level.txt
mudpyc/driver/__init__.py
mudpyc/driver/de/__init__.py
mudpyc/driver/de/morgengrauen.py
mudpyc/driver/en/__init__.py
mudpyc/driver/en/_lpmud.py
mudpyc/driver/en/midnightsun.py
mudpyc/mapper/__init__.py
mudpyc/mapper/const.py
mudpyc/mapper/main.py
mudpyc/mapper/spiral.py
mudpyc/mapper/sql.py
mudpyc/mapper/walking.py
util/gen-map.py