Metadata-Version: 1.2
Name: mudpyc
Version: 0.1.4
Summary: A MUD client
Home-page: http://github.com/smurfix/MudPyC
Author: Matthias Urlichs
Author-email: matthias@urlichs.de
License: GPLv3 or later
Keywords: async,mudlet,MUD
Platform: UNKNOWN
Classifier: License :: OSI Approved :: GNU General Public License v3 or later (GPLv3+)
Classifier: Operating System :: POSIX :: Linux
Classifier: Programming Language :: Python :: 3 :: Only
Classifier: Programming Language :: Python :: 3.7
Classifier: Programming Language :: Python :: 3.8
Classifier: Programming Language :: Python :: 3.9
Classifier: Programming Language :: Python :: Implementation :: CPython
Classifier: Programming Language :: Python :: Implementation :: PyPy
Classifier: Framework :: Trio
Requires-Python: >=3.6
